LICENSE
MANIFEST.in
README.rst
setup.py
django_blog_home.egg-info/PKG-INFO
django_blog_home.egg-info/SOURCES.txt
django_blog_home.egg-info/dependency_links.txt
django_blog_home.egg-info/top_level.txt
home/__init__.py
home/admin.py
home/apps.py
home/models.py
home/tests.py
home/urls.py
home/views.py
home/migrations/0001_initial.py
home/migrations/0002_auto_20190905_1810.py
home/migrations/0003_auto_20190905_1825.py
home/migrations/0004_auto_20190905_1830.py
home/migrations/0005_post_image.py
home/migrations/0006_auto_20190906_1033.py
home/migrations/__init__.py
home/static/bootstrap.min.css
home/templates/article.html
home/templates/home.html